{
  "main": {
    "id": "306d74399be4c842",
    "type": "split",
    "children": [
      {
        "id": "ffcf9371899696ab",
        "type": "tabs",
        "children": [
          {
            "id": "063fb31e4aa2261a",
            "type": "leaf",
            "state": {
              "type": "markdown",
              "state": {
                "file": "conflict-files-obsidian-git.md",
                "mode": "source",
                "source": false
              }
            }
          }
        ]
      }
    ],
    "direction": "vertical"
  },
  "left": {
    "id": "45bcdf8615ece8b5",
    "type": "split",
    "children": [
      {
        "id": "774b958f837d54dd",
        "type": "tabs",
        "children": [
          {
            "id": "10edfcd88b2b7064",
            "type": "leaf",
            "state": {
              "type": "file-explorer",
              "state": {
                "sortOrder": "alphabetical"
              }
            }
          },
          {
            "id": "46740e6c685cc375",
            "type": "leaf",
            "state": {
              "type": "search",
              "state": {
                "query": "",
                "matchingCase": false,
                "explainSearch": false,
                "collapseAll": false,
                "extraContext": false,
                "sortOrder": "alphabetical"
              }
            }
          },
          {
            "id": "e407e89ba1a72b9d",
            "type": "leaf",
            "state": {
              "type": "bookmarks",
              "state": {}
            }
          },
          {
            "id": "6616448615de7f38",
            "type": "leaf",
            "state": {
              "type": "surfing-tab-tree",
              "state": {}
            }
          }
        ]
      }
    ],
    "direction": "horizontal",
    "width": 300
  },
  "right": {
    "id": "c7470036265c6001",
    "type": "split",
    "children": [
      {
        "id": "da88690ba80de9eb",
        "type": "tabs",
        "children": [
          {
            "id": "3f81a9c940336ee3",
            "type": "leaf",
            "state": {
              "type": "calendar",
              "state": {}
            }
          },
          {
            "id": "f84851cc1e531c83",
            "type": "leaf",
            "state": {
              "type": "backlink",
              "state": {
                "file": "conflict-files-obsidian-git.md",
                "collapseAll": false,
                "extraContext": false,
                "sortOrder": "alphabetical",
                "showSearch": false,
                "searchQuery": "",
                "backlinkCollapsed": false,
                "unlinkedCollapsed": true
              }
            }
          },
          {
            "id": "39880e11769bde8e",
            "type": "leaf",
            "state": {
              "type": "outgoing-link",
              "state": {
                "file": "conflict-files-obsidian-git.md",
                "linksCollapsed": false,
                "unlinkedCollapsed": true
              }
            }
          },
          {
            "id": "0a32da2a3702bbc2",
            "type": "leaf",
            "state": {
              "type": "tag",
              "state": {
                "sortOrder": "frequency",
                "useHierarchy": true
              }
            }
          },
          {
            "id": "13866a872e7c80c6",
            "type": "leaf",
            "state": {
              "type": "outline",
              "state": {
                "file": "conflict-files-obsidian-git.md"
              }
            }
          }
        ]
      }
    ],
    "direction": "horizontal",
    "width": 300,
    "collapsed": true
  },
  "left-ribbon": {
    "hiddenItems": {
      "obsidian-excalidraw-plugin:Create new drawing": false,
      "table-editor-obsidian:Advanced Tables Toolbar": false,
      "obsidian-map-view:Open map view": false,
      "obsidian-day-planner:Timeline": false,
      "obsidian-leaflet-plugin:Open Leaflet Map": false,
      "obsidian-advanced-slides:Show Slide Preview": false,
      "obsidian-full-calendar:Open Full Calendar": false,
      "webpage-html-export:Export Vault to HTML": false,
      "surfing:surfing-bookmark-manager": false,
      "switcher:Apri selezione rapida": false,
      "graph:Apri vista grafo": false,
      "canvas:Crea nuova lavagna": false,
      "daily-notes:Apri nota del giorno": false,
      "templates:Inserisci modello": false,
      "command-palette:Apri riquadro comandi": false,
      "markdown-importer:Apri importazione Markdown": false
    }
  },
  "active": "063fb31e4aa2261a",
  "lastOpenFiles": [
    "conflict-files-obsidian-git.md"
  ]
}